{
  "cards": [
    {
      "id": "6d637784-b5e8-47d8-a937-b8e373663d5a",
      "title": "sadas",
      "task": [
        {
          "id": "4de6e2ea-97c0-4807-b46f-1da8f8aa8558",
          "taskName": "asdad",
          "taskDescription": "jhhjgjhgjgghjgjhhg"
        },
        {
          "id": "3aafb2d0-68a4-40be-9fd8-d76ecac66501",
          "taskName": "shubham ",
          "taskDescription": "jhhjgjhgjgghjgjhhg"
        }
      ]
    },
    {
      "id": "c96737a0-8e18-487c-9aa9-d864e0d6687a",
      "title": "Doing",
      "task": [
        {
          "id": "e7946a13-09b1-4818-b451-fda74e316bb6",
          "taskName": "sdasdajhdkhdkashdahdkahdkjashdkahdkaskdas",
          "taskDescription": "jhhjgjhgjgghjgjhhg"
        }
      ]
    }
  ]
}